OpenMechanochem.py
OpenMechanochem-1.0.1.dist-info/LICENSE
OpenMechanochem-1.0.1.dist-info/METADATA
OpenMechanochem-1.0.1.dist-info/WHEEL
OpenMechanochem-1.0.1.dist-info/entry_points.txt
OpenMechanochem-1.0.1.dist-info/top_level.txt
OpenMechanochem-1.0.1.dist-info/RECORD
