Metadata-Version: 2.1
Name: OpenMechanochem
Version: 1.0.1
Summary: python module for mechanochemical simulations
Home-page: https://github.com/danjodc/OpenMechanochem
Author: danjdc
Author-email: dechavezdanjo@gmail.com
License: GNU
Platform: UNKNOWN
Classifier: License :: OSI Approved :: GNU Lesser General Public License v2 or later (LGPLv2+)
Classifier: Programming Language :: Python
Classifier: Programming Language :: Python :: 3
Classifier: Programming Language :: Python :: 3.7
Classifier: Programming Language :: Python :: Implementation :: CPython
Classifier: Programming Language :: Python :: Implementation :: PyPy
Requires-Python: >=3.6.0
Requires-Dist: ase
Requires-Dist: numpy
